Lagrange/Lagrange.py
Lagrange/__init__.py
rkLagrange-0.0.1.dist-info/METADATA
rkLagrange-0.0.1.dist-info/WHEEL
rkLagrange-0.0.1.dist-info/top_level.txt
rkLagrange-0.0.1.dist-info/RECORD
